stac_nb/__init__.py
stac_nb/stac_nb.py
stac_nb-0.4.0.dist-info/LICENSE
stac_nb-0.4.0.dist-info/METADATA
stac_nb-0.4.0.dist-info/WHEEL
stac_nb-0.4.0.dist-info/top_level.txt
stac_nb-0.4.0.dist-info/RECORD
