Metadata-Version: 2.1
Name: stac-nb
Version: 0.4.0
Summary: stac-nb exposes STAC in Jupyter Notebooks
Home-page: https://github.com/darrenwiens/stac-nb
Author: Darren Wiens
Author-email: dkwiens@gmail.com
License: MIT license
Project-URL: Documentation, https://stac-nb.readthedocs.io
Project-URL: Source, https://github.com/darrenwiens/stac-nb
Project-URL: Tracker, https://github.com/darrenwiens/stac-nb/issues
Keywords: stac_nb
Platform: UNKNOWN
Classifier: Development Status :: 2 - Pre-Alpha
Classifier: Intended Audience :: Developers
Classifier: License :: OSI Approved :: MIT License
Classifier: Natural Language :: English
Classifier: Programming Language :: Python :: 3
Classifier: Programming Language :: Python :: 3.6
Classifier: Programming Language :: Python :: 3.7
Classifier: Programming Language :: Python :: 3.8
Requires-Python: >=3.6
Requires-Dist: ipywidgets (>=7.6.5)
Requires-Dist: jupyterlab (>=3.0.0)
Requires-Dist: pystac-client (>=0.3.0)
